ktianc/__init__.py
ktianc/main.py
ktianc-0.3.2.dist-info/METADATA
ktianc-0.3.2.dist-info/WHEEL
ktianc-0.3.2.dist-info/RECORD
