Metadata-Version: 2.1
Name: ktianc
Version: 0.3.2
Summary: ktianc first package
License: MIT
Author: ktianc
Author-email: 2445667550@qq.com
Requires-Python: >=3.10
Classifier: License :: OSI Approved :: MIT License
Classifier: Programming Language :: Python :: 3
Classifier: Programming Language :: Python :: 3.10
Classifier: Programming Language :: Python :: 3.11
Classifier: Programming Language :: Python :: 3.12
